LICENSE.txt
setup.py
AbMetaAnalysis/Clustering.py
AbMetaAnalysis/Defaults.py
AbMetaAnalysis/EDA.py
AbMetaAnalysis/Plot.py
AbMetaAnalysis/RepClassifier.py
AbMetaAnalysis/SubSample.py
AbMetaAnalysis/TestRepClassifier.py
AbMetaAnalysis/Utilities.py
AbMetaAnalysis/Version.py
AbMetaAnalysis/__init__.py
AbMetaAnalysis.egg-info/PKG-INFO
AbMetaAnalysis.egg-info/SOURCES.txt
AbMetaAnalysis.egg-info/dependency_links.txt
AbMetaAnalysis.egg-info/requires.txt
AbMetaAnalysis.egg-info/top_level.txt