Metadata-Version: 2.1
Name: AbMetaAnalysis
Version: 1.0.4
Summary: Package for Meta analysis of BCR repertoires 
Home-page: https://github.com/boazfran/AbMetaAnalysis
Author: Boaz Frankel
Author-email: boazfr@gmail.com
License: MIT (X11)
Platform: UNKNOWN
License-File: LICENSE.txt
